{"cameraMode":{"drawMode":0,"name":"Shaded","section":"Shading Mode"},"sceneLighting":true,"audioPlay":false,"sceneViewState":{"showFog":true,"showMaterialUpdate":false,"showSkybox":true,"showFlares":true,"showImageEffects":true,"showParticleSystems":true},"in2DMode":false,"pivot":{"x":-4.60678768157959,"y":0.9172844886779785,"z":-1.1840887069702149},"rotation":{"x":0.060255665332078937,"y":-0.02514096163213253,"z":0.0015137282898649574,"w":0.9978940486907959},"size":12.435935974121094,"orthographic":false}